{
  "pets": [
    {
      "id": 1,
      "name": "Áo thun nam nữ in chữ Ngủ ngon",
      "breed": "Vải thun",
      "sex": "Nam/ Nữ",
      "size": "Freesize",
      "image": "https://i.pinimg.com/736x/b2/3b/c0/b23bc074f047287a0b1b07df91c088e5.jpg",
      "code": "234985798247598",
      "location": "Tp Hồ Chí Minh"
    },
    {
      "id": 2,
      "name": "Áo thun nam nữ in hình con vịt",
      "breed": "Vải thun",
      "sex": "Nam/ Nữ",
      "size": "Freesize",
      "image": "https://i.pinimg.com/736x/8c/15/ee/8c15ee36e95744eb90862f779235d27c.jpg",
      "code": "234985798247598",
      "location": "Tp Hồ Chí Minh"
    },
    {
      "id": 3,
      "name": "Áo thun nam nữ in hình trứng",
      "breed": "Vải thun",
      "sex": "Nam/ Nữ",
      "size": "Freesize",
      "image": "https://i.pinimg.com/736x/3e/2b/c3/3e2bc3008f1eb2a6bfdbf463f1e049ed.jpg",
      "code": "320485904869080",
      "location": "Tp Hồ Chí Minh"
    },
    {
      "id": 4,
      "name": "Áo thun nam nữ in hình trứng",
      "breed": "Vải thun",
      "sex": "Nam/ Nữ",
      "size": "Freesize",
      "image": "https://i.pinimg.com/736x/b2/3b/c0/b23bc074f047287a0b1b07df91c088e5.jpg",
      "code": "320485904869080",
      "location": "Tp Hồ Chí Minh"
    },
    {
      "id": 5,
       "name": "Áo thun nam nữ in hình trứng",
      "breed": "Vải thun",
      "sex": "Nam/ Nữ",
      "size": "Freesize",
      "image": "https://i.pinimg.com/736x/3e/2b/c3/3e2bc3008f1eb2a6bfdbf463f1e049ed.jpg",
      "code": "320485904869080",
      "location": "Tp Hồ Chí Minh"
    },
    {
      "id": 6,
      "name": "Áo thun nam nữ in chữ Ngủ ngon",
      "breed": "Vải thun",
      "sex": "Nam/ Nữ",
      "size": "Freesize",
      "image": "https://i.pinimg.com/736x/b2/3b/c0/b23bc074f047287a0b1b07df91c088e5.jpg",
      "code": "234985798247598",
      "location": "Tp Hồ Chí Minh"
    },
    {
      "id": 7,
     "name": "Áo thun nam nữ in hình trứng",
      "breed": "Vải thun",
      "sex": "Nam/ Nữ",
      "size": "Freesize",
      "image": "https://i.pinimg.com/736x/b2/3b/c0/b23bc074f047287a0b1b07df91c088e5.jpg",
      "code": "320485904869080",
      "location": "Tp Hồ Chí Minh"
    },
    {
      "id": 8,
     "name": "Áo thun nam nữ in chữ Ngủ ngon",
      "breed": "Vải thun",
      "sex": "Nam/ Nữ",
      "size": "Freesize",
      "image": "https://i.pinimg.com/736x/b2/3b/c0/b23bc074f047287a0b1b07df91c088e5.jpg",
      "code": "234985798247598",
      "location": "Tp Hồ Chí Minh"
    }
  ]
}